Single_Cycle_Datapath/Data_mem.v
module data_memory(input[2:0] load_format,
input [1:0] store_format,
input mem_write_en,mem_read_en,
input[63:0] mem_addr, mem_data_input,
output reg [63:0] mem_data_output);
integer i;
reg [7:0] data_mem [2047:0];
//initlization of data memory
initial begin
  for (i=0;i<2047;i++)begin
   data_mem[i] <= 8'b0;
  end
end

always @(mem_write_en ==1 or mem_read_en==1) begin
  $display("mem_addr: %h, mem_data_input %h",mem_addr, mem_data_input);
//Store instructions
if(mem_write_en == 1 && mem_read_en == 0)begin
  $display("entered into store function");
  if (store_format == 3'b00) begin //Store byte
   $display("Entered into halfword loop, data_mem %h",data_mem[mem_addr]);
    data_mem[mem_addr]<= mem_data_input[7:0];
    ;
  end
  else if(store_format == 3'b01) begin //Store halfword
  $display("Entered into halfword loop, data_mem %h",{data_mem[mem_addr],data_mem[mem_addr+1]});
      data_mem[mem_addr] <= mem_data_input[7:0];
      data_mem[mem_addr + 1] <= mem_data_input [15:8];
  end
  else if(store_format == 3'b10) begin //store word
    $display("Entered into word loop, data_mem %h",{data_mem[mem_addr],data_mem[mem_addr+1],data_mem[mem_addr+2],data_mem[mem_addr+3]});
      data_mem[mem_addr] <= mem_data_input[7:0];
      data_mem[mem_addr + 1] <= mem_data_input [15:8];
      data_mem[mem_addr + 2] <= mem_data_input [23:16];
      data_mem[mem_addr + 3] <= mem_data_input[31:24];
  end
  else begin //Store doubleword
    
      data_mem[mem_addr] <= mem_data_input[7:0];
      data_mem[mem_addr + 64'd1] <= mem_data_input [15:8];
      data_mem[mem_addr + 64'd2] <= mem_data_input [23:16];
      data_mem[mem_addr + 64'd3] <= mem_data_input [31:24];
      data_mem[mem_addr + 64'd4] <= mem_data_input [39:32];
      data_mem[mem_addr + 64'd5] <= mem_data_input [47:40];
      data_mem[mem_addr + 64'd6] <= mem_data_input [55:48];
      data_mem[mem_addr + 64'd7] <= mem_data_input[63:56];
       $display("Entered into doubleword loop, data_mem %h",{data_mem[mem_addr],data_mem[mem_addr+1],data_mem[mem_addr+2],data_mem[mem_addr+3],
                      data_mem[mem_addr+4],data_mem[mem_addr+5],data_mem[mem_addr+6],data_mem[mem_addr+7]});
  end
  
end

else if (mem_write_en == 0 && mem_read_en == 1) begin
  if (load_format == 3'b000) begin  //load byte
    mem_data_output[7:0] <= data_mem[mem_addr];
    $display("Entered into load byte loop, data_mem %h",data_mem[mem_addr]);  
  end
  else if (load_format == 3'b001) begin //load halfword
      mem_data_output[7:0] <= data_mem[mem_addr];
      mem_data_output [15:8] <= data_mem[mem_addr + 1];
      $display("Entered into load halfword loop, data_mem %h",{data_mem[mem_addr+1],data_mem[mem_addr]});  
end
else if (load_format == 3'b010) begin //load word
      mem_data_output [7:0] <= data_mem[mem_addr];
      mem_data_output [15:8] <= data_mem[mem_addr + 1];
      mem_data_output [23:16] <= data_mem[mem_addr + 2];
      mem_data_output [31:24] <= data_mem[mem_addr+3]; 
       $display("Entered into load word loop, data_mem %h",{data_mem[mem_addr+3],data_mem[mem_addr+2],
                                                                  data_mem[mem_addr+1],data_mem[mem_addr]});        
end
else if (load_format == 3'b101) begin  //load doubleword

      mem_data_output [7:0] <= data_mem[mem_addr];
      mem_data_output [15:8] <= data_mem[mem_addr + 1];
      mem_data_output [23:16] <= data_mem[mem_addr + 2];
      mem_data_output [31:24] <= data_mem[mem_addr + 3];
      mem_data_output [39:32] <= data_mem[mem_addr + 4];
      mem_data_output [47:40] <= data_mem[mem_addr + 5];
      mem_data_output [55:48] <= data_mem[mem_addr + 6];
      mem_data_output [63:56] <= data_mem[mem_addr + 7]; 
       $display("Entered into load doubleword loop, data_mem %h",{data_mem[mem_addr+7],data_mem[mem_addr+6],data_mem[mem_addr+5],
                                                                  data_mem[mem_addr+4],data_mem[mem_addr+3],data_mem[mem_addr+2],
                                                                  data_mem[mem_addr+1],data_mem[mem_addr]});
end
end
end
endmodule

Single_Cycle_Datapath/Alu.v
/*module ALU_64bit_RISCV(input[3:0] Alu_opr,
                       input [63:0] IP_data1,IP_data2,
                       output reg [63:0] OP_data);

always @(*) begin
    $display("Entered into Alu_opr: %h", Alu_opr);
    $display("IP_data1: %h,  IP_data2: %h",IP_data1,IP_data2);
    case (Alu_opr)
    4'b0000: OP_data = IP_data1 + IP_data2;
    4'b0001: OP_data = IP_data1 - IP_data2;
    4'b0010: OP_data = IP_data1 << IP_data2;
    4'b0011: OP_data = IP_data1 ^ IP_data2;
    4'b0100: OP_data = IP_data1 >> IP_data2;
    4'b0101: OP_data = IP_data1 || IP_data2;
    4'b0110: OP_data = IP_data1 && IP_data2;
    4'b0111: begin
            if(IP_data1 == IP_data2)begin
              OP_data = 64'b0;
              $display("both data are equal");
            end
            else begin
                $display("both data are not equal");
              OP_data = 64'b1;
            end
            end
    4'b1000: begin
            if(IP_data1 != IP_data2)begin
              OP_data = 64'b0;
            end
            else begin
              OP_data = 64'b1;
            end
            end

    4'b1001: begin
            if(IP_data1 < IP_data2)begin
              OP_data = 64'b0;
            end
            else begin
              OP_data = 64'b1;
            end
            end

    4'b1010: begin
            if(IP_data1 >= IP_data2)begin
              OP_data = 64'b0;
            end
            else begin
              OP_data = 64'b1;
            end
            end
    default: OP_data = 64'bz;
    endcase
    $display("OP_data: %h", OP_data);
end
endmodule
*/

module ALU_64bit_RISCV(input[3:0] Alu_opr,
                       input [63:0] IP_data1,IP_data2,
                       output reg [63:0] OP_data);

always @(Alu_opr or IP_data2) begin
    $display("Entered into Alu_opr: %h", Alu_opr);
    $display("IP_data1: %h,  IP_data2: %h",IP_data1,IP_data2);
    OP_data = (Alu_opr == 4'b0000)? (IP_data1 + IP_data2): (Alu_opr == 4'b0001) ? (IP_data1 - IP_data2) : (Alu_opr == 4'b0010) ? (IP_data1 << IP_data2) :
              (Alu_opr == 4'b0011)? (IP_data1 ^ IP_data2): (Alu_opr == 4'b0100)? (IP_data1 >> IP_data2): (Alu_opr == 4'b0101)? (IP_data1 || IP_data2):
              (Alu_opr==4'b0110)? (IP_data1 && IP_data2): (Alu_opr==4'b0111)? ((IP_data1 == IP_data2)? 64'b0: 64'b1): (Alu_opr == 4'b1000)?
              ((IP_data1 != IP_data2) ? 64'b0: 64'b1):(Alu_opr == 4'b1001)? ((IP_data1 < IP_data2)? 64'b0: 64'b1): (Alu_opr == 4'b1010)?
              ((IP_data1 >= IP_data2)? 64'b0: 64'b1): 64'bz;
    $display("OP_data: %h", OP_data);
end
endmodule

Single_Cycle_Datapath/Reg_file.v
module Reg_file(input Wen, 
input [4:0] Rs1_addr,Rs2_addr, Rd_addr,
input [63:0] write_data,
output [63:0] Rs1_data,Rs2_data);

reg[63:0] register[31:0]; //32 registers of 64-bit (2^5 where 5 is size of address bus of instruction)
integer  i;

//Initilization of Registers with zero value
initial begin
  //$display("Entered into intial memory loop");
  for(i=0;i<32;i++)begin
    if(i==5'b10100) begin   //Giving some value at x14(hex & 20 in decimal) for the testing purpose
      register[i] = 64'h456701023D2;
    end
    else if(i== 5'b10101 )begin //Giving some value at x15(hex & 21 in decimal) for the testing purpose
     register[i]= 64'h012005C2;
    end
    else if(i== 5'b01010)begin  //Giving some value at xA(hex & 10 in decimal) for the testing purpose
      register[i] = 64'h0000000000000002;
    end
    else begin
      register[i]=64'd0; //intializing the memory with zero values
    end
  end
end

 assign Rs1_data = register[Rs1_addr];  //gives register value for input 1 of ALU
 assign Rs2_data = register[Rs2_addr];  //gives register value for input 2 of ALU
always @(Rs1_data or Rs2_data) begin
  $display("Rs1_data: %h, Rs2_data: %h", Rs1_data,Rs2_data);
end
//Checks the Write enable bit then assigns the value to the particular register  
always @(posedge Wen or write_data )begin
  if(Wen)begin
  // $display("Entered into write loop");
  register[Rd_addr] = write_data;
  $monitor("Rd_addr: %h, mem[Rd_addr]: %h",Rd_addr,register[Rd_addr]);
end
end
endmodule

Single_Cycle_Datapath/decoder.v
module Decoder_64_bit_RISC(
input [31:0] input_inst,
output reg [3:0] Alu_opr,load_flag,
output reg [1:0] store_flag,
output reg [4:0] Rd_addr, Rs1_addr,Rs2_addr,
output reg reg_write_en,mem_write_en,mem_read_en,branch_en);


//This function finds the sub instruction of R-type
function [3:0]Alu_opr_R;
input [2:0] func3;
input [0:6] func7;
    
case ({func3,func7})
10'b0000000000: Alu_opr_R = 0000; //ADD instruction
10'b0000100000: Alu_opr_R = 0001; //SUB instruction
10'b0010000000: Alu_opr_R = 0010;//Sll instruction 
10'b1000000000: Alu_opr_R = 0011;//xor instruction
10'b1010000000: Alu_opr_R = 0100;//srl instruction
10'b1010100000: Alu_opr_R = 0101;//sra instruction
10'b1100000000: Alu_opr_R = 0110;//OR instruction
10'b1110000000: Alu_opr_R = 0111;//AND instruction
10'b0100000000: Alu_opr_R = 1000;//SLT instruction
default: Alu_opr_R = 1111; //NOP
endcase
endfunction


function [2:0]Alu_opr_I;
input [2:0] func3;
    
case (func3)
3'b000: Alu_opr_I = 0000; //addi instruction
3'b001: Alu_opr_I = 0010; //Slli instruction
3'b100: Alu_opr_I = 0011;//xori instruction
3'b101: Alu_opr_I = 0100;//srli instruction
//1010 Alu_opr_R = 0101;//srai instruction
3'b110: Alu_opr_I = 0110;//ORi instruction
3'b111: Alu_opr_I = 0111;//AND instruction
default: Alu_opr_I = 1111; //NOP
endcase
endfunction



function [2:0]Alu_opr_B;
input [2:0] func3;
    
case (func3)
3'b000: Alu_opr_B = 0111; //beq instruction
3'b001: Alu_opr_B = 1000; //Bne instruction
3'b100: Alu_opr_B = 1001;//blt instruction
3'b101: Alu_opr_B = 1010;//bge instruction
//1010 Alu_opr_R = 0101;//srai instruction
3'b110: Alu_opr_B = 0110;//bltu instruction
3'b111: Alu_opr_B = 0111;//bgeu instruction
default: Alu_opr_B = 1111; //NOP
endcase
endfunction

function [1:0]store_format;
input [2:0] func3;
    
case (func3)
3'b000: store_format = 00; //Store byte instruction
3'b001: store_format = 01; //Store halfword instruction
3'b010: store_format = 10;//Store word instruction
3'b011: store_format = 11;//Store doubleword
default: store_format = 2'bz; //NOP
endcase
endfunction

function [2:0]load_format;
input [2:0] func3;
case (func3)
3'b000: load_format = 000; //Load byte instruction
3'b001: load_format = 001; //Load halfword instruction
3'b010: load_format = 010;//Load word instruction
3'b100: load_format = 011;// Load unsigned byte
3'b101: load_format = 100; //load unsigned halfword
3'b011: load_format = 101;//Load doubleword instruction
default: load_format = 111; //NOP
endcase
endfunction

//always @(posedge clk)begin
always @(input_inst) begin
  $display("input_inst: %h",input_inst );
/*inst_format = inst_type();
$display("inst_format: %h", inst_format);
$display("input_inst[6:0] = %h",input_inst[6:0] );*/
case (input_inst[6:0])
//R-Register instructions
7'b0110011: begin
  Rs1_addr = input_inst[19:15];
  Rs2_addr = input_inst[24:20];
  Rd_addr =  input_inst[11:7];
  reg_write_en=1'b1;
  mem_write_en=1'b0;
  mem_read_en=1'b0;
  branch_en = 1'b0;
  Alu_opr = Alu_opr_R(input_inst[14:12],input_inst[31:25]);
end
//I-immediate instructions
7'b0010011: begin 
  $display("Entered into immediate loop");
  Rs1_addr = input_inst[19:15];
  Rs2_addr = 5'bz;
  Rd_addr =  input_inst[11:7];
  reg_write_en=1'b1;
  mem_write_en=1'b0;
  mem_read_en=1'b0;
  branch_en = 1'b0;
  Alu_opr = Alu_opr_I(input_inst[14:12]);
end
//Load-instruction
7'b0000011: begin
  Rs1_addr = input_inst[19:15];
  Rs2_addr = 5'bz;
  Rd_addr =  input_inst[11:7];
  reg_write_en=1'b1;
  mem_write_en=1'b0;
  mem_read_en=1'b1;
  branch_en = 1'b0;
  load_flag = load_format(input_inst[14:12]);
  Alu_opr = 0000;
end
//Store Instruction
7'b0100011: begin
  //immed[4:0]= input_inst[11:7];
  //immed[11:5]= input_inst[31:25];
  Rs1_addr = input_inst[19:15];
  Rs2_addr = input_inst[24:20];
  Rd_addr = 5'bz;
  Alu_opr = 0000;
  store_flag=store_format(input_inst[14:12]);
  reg_write_en=1'b0;
  mem_write_en=1'b1;
  mem_read_en=1'b0;
  branch_en = 1'b0;
end
//Branch Instruction
7'b1100111: begin
  //immed[11] = input_inst[31];
  //immed[10] = input_inst[7];
  //immed[3:0] = input_inst[11:8];
  //immed[9:4] = input_inst[30:25];
  $display("Entered into branch loop");
  Rs1_addr = input_inst[19:15];
  Rs2_addr = input_inst[24:20];
  Alu_opr = Alu_opr_B(input_inst[14:12]);
  reg_write_en=1'b0;
  mem_write_en=1'b0;
  mem_read_en=1'b0;
  branch_en = 1'b1;
end
default: begin
 Rs1_addr= 5'bz;
 Rs2_addr = 5'bz;
 Rd_addr = 5'bz;
 //immed = 12'bz;
 Alu_opr = 4'bz;
  reg_write_en=1'b0;
  mem_write_en=1'b0;
  mem_read_en=1'b0;
  branch_en=1'b0;
end
endcase
$display("Alu_opr: %b, Rd_addr: %b , Rs1_addr: %b, Rs2_addr: %b, reg_write_en: %b",Alu_opr, Rd_addr,Rs1_addr,Rs2_addr,reg_write_en);
end
endmodule

Single_Cycle_Datapath/Fetch.v

module fetch_RISCV(input clk,branch_en,
input[63:0] Alu_output,
output reg [63:0] PC);
initial begin
    PC=32'b0;
end
//reg[31:0] PC;
always @(posedge clk) begin
    if(branch_en == 1) begin
      PC<=Alu_output;
    end
    else begin
    PC <=  PC + 4;
    end
    
    //$display("clk: %b, PC: %h", clk,PC);
end
//always @()
endmodule

module instruction_mem(input[31:0] PC,output reg[31:0] instr);

reg[7:0] byte_instr[65535:0];
initial begin
   //32'h015A04B3  ADD X9, X14 ,X15
   byte_instr[64'h0000000000000004]<=8'hB3;
   byte_instr[64'h0000000000000005]<=8'h04;
   byte_instr[64'h0000000000000006]<=8'h5A;
   byte_instr[64'h0000000000000007]<=8'h01;

   //32'h00148493 ADDi xB, x9, 1 add 1 to the value of x9 register
   byte_instr[64'h0000000000000008]<=8'h93;
   byte_instr[64'h0000000000000009]<=8'h84;
   byte_instr[64'h000000000000000A]<=8'h14;
   byte_instr[64'h000000000000000B]<=8'h00;

   //32'h0E953823 SD X9,240(x10) doubleword
   byte_instr[64'h000000000000000C]<=8'h23;
   byte_instr[64'h000000000000000D]<=8'h38;
   byte_instr[64'h000000000000000E]<=8'h95;
   byte_instr[64'h000000000000000F]<=8'h0E; 

   //32'h0F053283 LD x5,240(x10)  doubleword
   byte_instr[64'h0000000000000010]<=8'h83;
   byte_instr[64'h0000000000000011]<=8'h32;
   byte_instr[64'h0000000000000012]<=8'h05;
   byte_instr[64'h0000000000000013]<=8'h0F;

   //32'h02548167 Beq x5,x9,11(hex and 17 in decimal)
   byte_instr[64'h0000000000000014]<=8'h67;
   byte_instr[64'h0000000000000015]<=8'h81;
   byte_instr[64'h0000000000000016]<=8'h54;
   byte_instr[64'h0000000000000017]<=8'h02; 

   //32'h00148593 ADDi xB, x9, 1 add 1 to the value of x9 register
   byte_instr[64'h0000000000000025]<=8'h93;
   byte_instr[64'h0000000000000026]<=8'h85;
   byte_instr[64'h0000000000000027]<=8'h14;
   byte_instr[64'h0000000000000028]<=8'h00;


end

always @(PC)begin
    $display("PC: %h", PC);
 instr[7:0] <= byte_instr[PC];
 instr[15:8] <= byte_instr[PC+1];
 instr[23:16] <= byte_instr[PC+2];
 instr[31:24] <= byte_instr[PC+3];
// $display("instr[31:0]: %h",instr);
end
endmodule


module clk_input(output reg clk);
initial begin
  $dumpfile("Single_datapath_log.vcd");
  $dumpvars;
  #200;
  $finish;
end
initial begin
    clk=0;
end
always #15 clk= ~clk;

endmodule

Single_Cycle_Datapath/Single_datapath.v
`timescale 1ns/1ps

`include "decoder.v"
`include "Alu.v"
`include "Data_mem.v"
`include "Reg_file.v"
`include "Fetch.v"


//module Single_datapath(input[31:0] instr,input clk);
module Single_datapath();
reg [3:0] Alu_opr,load_flag;
reg [1:0] store_flag;
reg [4:0] Rd_addr, Rs1_addr,Rs2_addr;
wire[63:0] Alu_output;
wire [63:0] Rs1_data,Rs2_data,input2_data;
reg reg_write_en,mem_write_en,mem_read_en,branch_en;
wire [63:0] reg_file_input, mem_data_output;
wire clk;
wire[31:0] pc;
wire[31:0] instr;
wire [63:0] branch_addr;

  clk_input U1(clk);
  fetch_RISCV U2(clk,branch_en,branch_addr,pc);
  assign branch_addr = (Alu_output == 64'b0 && branch_en==1)? (pc+{instr[31],instr[7],instr[30:25],instr[11:8]}): 64'bz;
  instruction_mem U3(pc,instr);
  /*Decode the instruction and fetch the ALU operation, load instruction type, store instruction type, destination register address, Input 1 & 2's register addresses,
  Register file write enable, data memory write enable, data memory read enable*/
  Decoder_64_bit_RISC U4(instr,Alu_opr,load_flag,store_flag,Rd_addr,Rs1_addr,Rs2_addr,reg_write_en,mem_write_en,mem_read_en,branch_en);

  //Fetch the data value from register file for input data 1 and input data 2
  Reg_file U5(reg_write_en,Rs1_addr,Rs2_addr,Rd_addr,reg_file_input,Rs1_data,Rs2_data);

  //Assign the 2nd input to ALU as per the type of instruction
  assign input2_data = (instr[6:0] == 7'b0110011 || instr[6:0]==7'b1100111) ? Rs2_data : //R-type instruction's register value
                        (instr[6:0] == 7'b0010011 || instr[6:0] == 7'b0000011 )? {52'b0,instr[31:20]} : //I-type & L-Load type instruction's immediate value
                        (instr[6:0] == 7'b0100011) ? {instr[31:25],instr[11:7]} : //Store instruction's immediate value
                        64'bz;
                        //{instr[31],instr[7],instr[30:25],instr[11:8]};  //Branch instruction's immediate value

  //ALU performs the operation as per the instruction
  ALU_64bit_RISCV U6(Alu_opr,Rs1_data,input2_data,Alu_output);
  
  //Data memory is of 2047 x 8 means 8-bit as RISC V has byte addressable memory.
  data_memory U7(load_flag,store_flag,mem_write_en,mem_read_en,Alu_output,Rs2_data,mem_data_output);

  //This is a mux having two inputs with one select line.It provides the data memory output if instruction is load else provides the alu output to the register file 
  assign reg_file_input = (mem_read_en == 1 && mem_write_en == 0 && reg_write_en== 1)? mem_data_output:Alu_output; 
/*always@ (posedge instr)begin
   $monitor("Wen: %b,Rs1_addr: %h,Rs2_addr: %h,Wd_addr: %h,write_data: %h,Rs1_data: %h,Rs2_data: %h, alu_output: %h", Wen,Rs1_addr,Rs2_addr,Wd_addr,write_data,Rs1_data,Rs2_data,Alu_output);
end*/
endmodule

Single_Cycle_Datapath/Single_datapath_log.vcd
$date
	Thu Jun 17 19:14:39 2021
$end

$version
	Synopsys VCS version I-2014.03-2
$end

$timescale
	1ps
$end

$comment Csum: 1 269ae253970cece3 $end


$scope module Single_datapath $end
$var reg 4 ! Alu_opr [3:0] $end
$var reg 4 " load_flag [3:0] $end
$var reg 2 # store_flag [1:0] $end
$var reg 5 $ Rd_addr [4:0] $end
$var reg 5 % Rs1_addr [4:0] $end
$var reg 5 & Rs2_addr [4:0] $end
$var wire 64 ' Alu_output [63:0] $end
$var wire 64 ( Rs1_data [63:0] $end
$var wire 64 ) Rs2_data [63:0] $end
$var wire 64 * input2_data [63:0] $end
$var reg 1 + reg_write_en $end
$var reg 1 , mem_write_en $end
$var reg 1 - mem_read_en $end
$var reg 1 . branch_en $end
$var wire 64 / reg_file_input [63:0] $end
$var wire 64 0 mem_data_output [63:0] $end
$var wire 1 1 clk $end
$var wire 32 2 pc [31:0] $end
$var wire 32 3 instr [31:0] $end
$var wire 64 4 branch_addr [63:0] $end

$scope module U1 $end
$var reg 1 5 clk $end
$upscope $end


$scope module U2 $end
$var wire 1 1 clk $end
$var wire 1 . branch_en $end
$var wire 64 4 Alu_output [63:0] $end
$var reg 64 6 PC [63:0] $end
$upscope $end


$scope module U3 $end
$var wire 32 2 PC [31:0] $end
$var reg 32 7 instr [31:0] $end
$upscope $end


$scope module U4 $end
$var wire 32 3 input_inst [31:0] $end
$var reg 4 ! Alu_opr [3:0] $end
$var reg 4 " load_flag [3:0] $end
$var reg 2 # store_flag [1:0] $end
$var reg 5 $ Rd_addr [4:0] $end
$var reg 5 % Rs1_addr [4:0] $end
$var reg 5 & Rs2_addr [4:0] $end
$var reg 1 + reg_write_en $end
$var reg 1 , mem_write_en $end
$var reg 1 - mem_read_en $end
$var reg 1 . branch_en $end

$scope function Alu_opr_R $end
$var reg 4 8 Alu_opr_R [3:0] $end
$var reg 3 9 func3 [2:0] $end
$var reg 7 : func7 [0:6] $end
$upscope $end


$scope function Alu_opr_I $end
$var reg 3 ; Alu_opr_I [2:0] $end
$var reg 3 < func3 [2:0] $end
$upscope $end


$scope function Alu_opr_B $end
$var reg 3 = Alu_opr_B [2:0] $end
$var reg 3 > func3 [2:0] $end
$upscope $end


$scope function store_format $end
$var reg 2 ? store_format [1:0] $end
$var reg 3 @ func3 [2:0] $end
$upscope $end


$scope function load_format $end
$var reg 3 A load_format [2:0] $end
$var reg 3 B func3 [2:0] $end
$upscope $end

$upscope $end


$scope module U5 $end
$var wire 1 + Wen $end
$var wire 5 % Rs1_addr [4:0] $end
$var wire 5 & Rs2_addr [4:0] $end
$var wire 5 $ Rd_addr [4:0] $end
$var wire 64 / write_data [63:0] $end
$var wire 64 ( Rs1_data [63:0] $end
$var wire 64 ) Rs2_data [63:0] $end
$var integer 32 C i $end
$upscope $end


$scope module U6 $end
$var wire 4 ! Alu_opr [3:0] $end
$var wire 64 ( IP_data1 [63:0] $end
$var wire 64 * IP_data2 [63:0] $end
$var reg 64 D OP_data [63:0] $end
$upscope $end


$scope module U7 $end
$var wire 3 E load_format [2:0] $end
$var wire 2 # store_format [1:0] $end
$var wire 1 , mem_write_en $end
$var wire 1 - mem_read_en $end
$var wire 64 ' mem_addr [63:0] $end
$var wire 64 ) mem_data_input [63:0] $end
$var reg 64 F mem_data_output [63:0] $end
$var integer 32 G i $end
$upscope $end

$upscope $end

$enddefinitions $end

#0
$dumpvars
05
x.
01
x-
x,
x+
bxxxx !
bxxx =
bxxx >
bxxx ;
bxxx <
bxxxx 8
bxxx 9
bxxxxxxx :
bxxxxxxxxxxxxxxxxxxxxxxxxxxxxxxxxxxxxxxxxxxxxxxxxxxxxxxxxxxxxxxxx '
bxxxxxxxxxxxxxxxxxxxxxxxxxxxxxxxxxxxxxxxxxxxxxxxxxxxxxxxxxxxxxxxx D
b0000000000000000000000000000000000000000000000000000000000000000 6
bxxxxx $
bxxxxx %
bxxxxxxxxxxxxxxxxxxxxxxxxxxxxxxxxxxxxxxxxxxxxxxxxxxxxxxxxxxxxxxxx (
bxxxxx &
bxxxxxxxxxxxxxxxxxxxxxxxxxxxxxxxxxxxxxxxxxxxxxxxxxxxxxxxxxxxxxxxx )
bxxxxxxxxxxxxxxxxxxxxxxxxxxxxxxxx 7
b00000000000000000000011111111111 G
bxxxxxxxxxxxxxxxxxxxxxxxxxxxxxxxxxxxxxxxxxxxxxxxxxxxxxxxxxxxxxxxx F
bxxxxxxxxxxxxxxxxxxxxxxxxxxxxxxxxxxxxxxxxxxxxxxxxxxxxxxxxxxxxxxxx 4
b00000000000000000000000000100000 C
bxxxxxxxxxxxxxxxxxxxxxxxxxxxxxxxxxxxxxxxxxxxxxxxxxxxxxxxxxxxxxxxx *
bxxxxxxxxxxxxxxxxxxxxxxxxxxxxxxxx 3
bxxxx "
bxxx B
bxxx A
bxxxxxxxxxxxxxxxxxxxxxxxxxxxxxxxxxxxxxxxxxxxxxxxxxxxxxxxxxxxxxxxx 0
b00000000000000000000000000000000 2
bxxxxxxxxxxxxxxxxxxxxxxxxxxxxxxxxxxxxxxxxxxxxxxxxxxxxxxxxxxxxxxxx /
bxx #
bxxx @
bxx ?
bxxx E
$end
#15000
15
11
b0000000000000000000000000000000000000000000000000000000000000100 6
b00000000000000000000000000000100 2
b00000001010110100000010010110011 7
b00000001010110100000010010110011 3
b000 9
b0000000 :
b0000 8
b10100 %
b0000000000000000000001000101011001110000000100000010001111010010 (
b10101 &
b0000000000000000000000000000000000000001001000000000010111000010 )
b01001 $
1+
0,
0-
0.
b0000 !
b0000000000000000000000000000000000000001001000000000010111000010 *
bzzzzzzzzzzzzzzzzzzzzzzzzzzzzzzzzzzzzzzzzzzzzzzzzzzzzzzzzzzzzzzzz 4
b0000000000000000000001000101011001110001001100000010100110010100 D
b0000000000000000000001000101011001110001001100000010100110010100 '
b0000000000000000000001000101011001110001001100000010100110010100 /
#30000
05
01
#45000
15
11
b0000000000000000000000000000000000000000000000000000000000001000 6
b00000000000000000000000000001000 2
b00000000000101001000010010010011 7
b00000000000101001000010010010011 3
b0000000000000000000000000000000000000000000000000000000000000001 *
b000 <
b000 ;
b01001 %
b0000000000000000000001000101011001110001001100000010100110010100 (
bzzzzz &
bxxxxxxxxxxxxxxxxxxxxxxxxxxxxxxxxxxxxxxxxxxxxxxxxxxxxxxxxxxxxxxxx )
b0000000000000000000001000101011001110001001100000010100110010101 D
b0000000000000000000001000101011001110001001100000010100110010101 '
b0000000000000000000001000101011001110001001100000010100110010101 /
b0000000000000000000001000101011001110001001100000010100110010101 (
#60000
05
01
#75000
15
11
b0000000000000000000000000000000000000000000000000000000000001100 6
b00000000000000000000000000001100 2
b00001110100101010011100000100011 7
b00001110100101010011100000100011 3
b0000000000000000000000000000000000000000000000000000000011110000 *
b011 @
b11 ?
b01010 %
b0000000000000000000000000000000000000000000000000000000000000010 (
b01001 &
b0000000000000000000001000101011001110001001100000010100110010101 )
bzzzzz $
b11 #
0+
1,
b0000000000000000000000000000000000000000000000000000000011110010 D
b0000000000000000000000000000000000000000000000000000000011110010 '
b0000000000000000000000000000000000000000000000000000000011110010 /
#90000
05
01
#105000
15
11
b0000000000000000000000000000000000000000000000000000000000010000 6
b00000000000000000000000000010000 2
b00001111000001010011001010000011 7
b00001111000001010011001010000011 3
b011 B
b101 A
bzzzzz &
bxxxxxxxxxxxxxxxxxxxxxxxxxxxxxxxxxxxxxxxxxxxxxxxxxxxxxxxxxxxxxxxx )
b00101 $
1+
0,
1-
b0101 "
b101 E
bxxxxxxxxxxxxxxxxxxxxxxxxxxxxxxxxxxxxxxxxxxxxxxxxxxxxxxxxxxxxxxxx /
b0000000000000000000001000101011001110001001100000010100110010101 F
b0000000000000000000001000101011001110001001100000010100110010101 0
b0000000000000000000001000101011001110001001100000010100110010101 /
#120000
05
01
#135000
15
11
b0000000000000000000000000000000000000000000000000000000000010100 6
b00000000000000000000000000010100 2
b00000010010101001000000101100111 7
b00000010010101001000000101100111 3
bxxxxxxxxxxxxxxxxxxxxxxxxxxxxxxxxxxxxxxxxxxxxxxxxxxxxxxxxxxxxxxxx *
b000 >
b111 =
b01001 %
b0000000000000000000001000101011001110001001100000010100110010101 (
b00101 &
b0000000000000000000001000101011001110001001100000010100110010101 )
b0111 !
0+
0-
1.
b000000000000000000000000000000000000000000000000000000000000000x D
b000000000000000000000000000000000000000000000000000000000000000x '
b0000000000000000000001000101011001110001001100000010100110010101 *
b000000000000000000000000000000000000000000000000000000000000000x /
bxxxxxxxxxxxxxxxxxxxxxxxxxxxxxxxxxxxxxxxxxxxxxxxxxxxxxxxxxxxxxxxx 4
b0000000000000000000000000000000000000000000000000000000000000000 D
b0000000000000000000000000000000000000000000000000000000000000000 '
b0000000000000000000000000000000000000000000000000000000000100101 4
b0000000000000000000000000000000000000000000000000000000000000000 /
#150000
05
01
#165000
15
11
b0000000000000000000000000000000000000000000000000000000000100101 6
b00000000000000000000000000100101 2
b0000000000000000000000000000000000000000000000000000000000110110 4
b00000000000101001000010110010011 7
b00000000000101001000010110010011 3
b0000000000000000000000000000000000000000000000000000000000000001 *
b0000000000000000000000000000000000000000000000000000010000101010 4
bzzzzz &
bxxxxxxxxxxxxxxxxxxxxxxxxxxxxxxxxxxxxxxxxxxxxxxxxxxxxxxxxxxxxxxxx )
b01011 $
1+
0.
b0000 !
b0000000000000000000001000101011001110001001100000010100110010110 D
b0000000000000000000001000101011001110001001100000010100110010110 '
bzzzzzzzzzzzzzzzzzzzzzzzzzzzzzzzzzzzzzzzzzzzzzzzzzzzzzzzzzzzzzzzz 4
b0000000000000000000001000101011001110001001100000010100110010110 /
#180000
05
01
#195000
15
11
b0000000000000000000000000000000000000000000000000000000000101001 6
b00000000000000000000000000101001 2
bxxxxxxxxxxxxxxxxxxxxxxxxxxxxxxxx 7
bxxxxxxxxxxxxxxxxxxxxxxxxxxxxxxxx 3
bxxxxxxxxxxxxxxxxxxxxxxxxxxxxxxxxxxxxxxxxxxxxxxxxxxxxxxxxxxxxxxxx *
bzzzzz %
bxxxxxxxxxxxxxxxxxxxxxxxxxxxxxxxxxxxxxxxxxxxxxxxxxxxxxxxxxxxxxxxx (
bzzzzz $
bzzzz !
0+
bxxxxxxxxxxxxxxxxxxxxxxxxxxxxxxxxxxxxxxxxxxxxxxxxxxxxxxxxxxxxxxxx D
bxxxxxxxxxxxxxxxxxxxxxxxxxxxxxxxxxxxxxxxxxxxxxxxxxxxxxxxxxxxxxxxx '
bxxxxxxxxxxxxxxxxxxxxxxxxxxxxxxxxxxxxxxxxxxxxxxxxxxxxxxxxxxxxxxxx /
